{
  "title": "闪避",
  "content": "玩家使用黑腰带闪避来自骷髅的攻击。\n闪避是消除伤害的效果。它会将玩家受伤时通常会施加的负面影响完全地无效化，这包括伤害本身、击退、和任何新施加的减益。一些物品提供在受伤时激活闪避的几率（或必定激活）。\n几乎所有伤害来源都可以被闪避，包括敌怪攻击，如多刺灌木、机关、或熔岩等环境危险，以及掉落伤害。来自减益的伤害和其他间接伤害来源无法被闪避。\n\n目录\n\n1 来源\n2 例外\n\n2.1 敌怪攻击\n2.2 其他\n\n3 备注\n4 小贴士\n5 花絮\n敌怪攻击\n  电脑版//：此章节的信息仅适用于的《泰拉瑞亚》。\n以下敌怪的部分或所有攻击不可闪避。[1]\n\n敌怪\n不可闪避的攻击\n\n骷髅\n\n尝试打开高门时的所有攻击\n\n地牢守卫\n\n所有攻击\n\n光之女皇\n\n白天时的接触伤害\n伤害不少于 9999 的射弹（即暴怒状态下的射弹）\n\n其他\n溺水\n造成持续伤害的减益，如着火了！\n试图逃离血肉墙（惊恐）\n混沌状态激活时使用混沌传送杖\n备注\n进行闪避会提供 1.33 秒所有类型的无敌帧。装备十字项链或其升级物时，无敌帧时长提升至 2 秒。\n反弹伤害的效果（荆棘增益、海龟盔甲、和仙人掌盔甲）在攻击被闪避时依然会正常触发。\n黑腰带/忍者大师装备和混乱之脑的闪避优先级高于神圣防护。如果在神圣防护增益激活时，这些物品成功地产生了闪避，则此增益会被保留以应对下次受击。[2]\n来自圣骑士护盾和同伴方块增益的伤害可以被闪避。\n小贴士\n来自混乱之脑的闪避几率与来自黑腰带或忍者大师装备的闪避几率可以叠加，最终闪避几率约为 1/4 (25%)。不过，黑腰带和忍者大师装备无法叠加。\n（平均）每四次攻击消除一次的能力在防御不足以无效化高伤害的情况下非常有帮助，例如大师模式。对于高速移动或者发射大量射弹的 Boss，这也会让战斗变得显著更容易。\n花絮\n在 PvP 中，尽管会正常受到伤害（和其他负面影响），闪避来自其他玩家的攻击仍然会触发视觉效果。\n“一击必杀”的攻击现在不能通过闪避效果来避免了。\n在普通骷髅试图打开高门时，其伤害无法被闪避效果所闪避。\n\n混乱之脑现在提供闪避效果。\n移除了暗影躲避；其效果现在由神圣防护提供。\n\n攻击速度\n自动挥舞\n暴击\n伤害\n无敌帧\n击退\n锁定(电脑版、、、和)\n仆从\n射弹速度\n环境\n环境物体\n环境实体()\n生物群系背景\n生物群系\n蔓延\n日夜更替\n事件\n重力\n液体\n月相\n音乐\nNPC 消失\nNPC 生成\n状态讯息\n风\n界面\nBoss 生命条()\n相机模式(电脑版)\n制作人员名单()\n表情()\n小地图\nLogo\nNPC 旗号\n标题讯息(电脑版)\n小贴士\n资源包(电脑版)\n创意工坊中心(电脑版)\n物品\n可选择制作材料\n物块交换()\n消耗品\n制作站\n徒手\n联动内容\n防爆物体\n平坦表面物品\n挖矿速度\n修饰语\nNPC 掉落\n放置\n镐力\n稀有度\n配方\n收纳\n工具提示\n使用时间\n价值\n游戏\n成就()\n难度\n旅行()\n经典\n专家()\n钱币拾取\n大师()\n钓鱼\n高尔夫()\nHoik\n音乐\n晶塔()\n城镇()\n多人模式\n服务器\n聊天\n多人模式\n玩家\n仇恨\n弹药节约\n呼吸计\n增益和减益\n人物\n人物风格()\n伤害减免\n猛冲\n死亡\n防御\n闪避\n溺水\n附加跳\n掉落伤害\n鬼魂()\n发型\n生命\n生命再生\n物品栏\n生命偷取\n配装()\n运气()\n魔力\n移动速度\n社交栏\n生成\n隐形\n设置\n光标模式\n游戏控制\n照明模式()\n视差()\n设置(电脑版、、、和)\n切换键\n技术\nAI\n命令行参数\nConfig.json\n数据 ID\n游戏平台\nNPC 名字\n射弹\n世界\n困难模式\n困难模式转换\n困难模式之前\n秘密种子()\n世界\n生成\n世界种子()\n世界大小",
  "content_length": 1516,
  "chinese_ratio": 0.958,
  "categories": [
    "游戏机制"
  ]
}