{
  "title": "冰雪镰刀",
  "content": "来自 经典 专家 大师实体数量几率冰雪人鱼 冰雪人鱼1() 1% /  0.56%冰雪精 冰雪精1() 1% /  0.56%冰雪陆龟 冰雪陆龟11% () 0.56% 装甲维京海盗 装甲维京海盗1() 1% /  0.56%\n不要与死神镰刀或镰刀相混淆。\n 使用中的冰雪镰刀。\n冰雪镰刀是一个困难模式剑，当它挥动时，它会发射一个旋转的蓝色镰刀射弹，造成武器67%的伤害(33 基础伤害)，且最多可以穿透3个敌怪。射弹会逐渐减速，在移动3秒后消散。它可以由装甲维京海盗、冰雪精、冰雪陆龟、和冰雪人鱼以1/100 (1%)的概率掉落。\n其最佳修饰语是传奇。\n\n目录\n\n1 备注\n2 小贴士\n3 花絮\n备注\n冰雪镰刀射弹命中后产生8 嘀嗒[1]的静态无敌帧[2]\n像死神镰刀一样，这把武器的射弹的距离会随近战速度增加而变远。\n小贴士\n该武器对于近距离控场非常有效，因为大多数敌怪会在试图穿过悬停的射弹时被击退并受到大量伤害。它也可以作为对抗蠕虫类敌怪（如毁灭者、沙虫、和吞世怪）的有力武器——每个射弹都可以对这类敌怪造成多段伤害。\n花絮\n其英文名称“Ice Sickle”（冰雪镰刀）是对词语“icicle”（冰柱）的文字游戏。\nIce Sickle 的英文名称其实不太恰当，由于它的柄比镰刀长，其刃部没有镰刀那么弯曲，因而它更像现实生活中的 scythe（大镰，其柄比镰刀更长）而非 sickle（镰刀）。\n射弹伤害从造成基础伤害的 50% 提升至 67%.\n射弹的穿透数量从 3 提升至 4。\n\n伤害由 42 提升至 50。\n冰雪镰刀射弹的范围提升 50%。\n射弹伤害由基础伤害的 100% 降低至 50%。\n射弹改为使用静态无敌帧，并降低了命中间的静态无敌时间（会略微更频繁地造成基础伤害）。\n射弹的穿透数量由 5 降低至 3。\n掉落几率由 1/180 提升至 1/100。任天堂任天堂3DS正式版：引入。\n召唤武器仆从\n雀杖()\n史莱姆法杖\n小雪怪法杖()\n阿比盖尔的花()\n吸血鬼青蛙法杖()\n黄蜂法杖()\n小鬼法杖()\n刃杖()\n蜘蛛法杖()\n血红法杖()\n魔眼法杖()\n海盗法杖()\n矮人法杖\n沙漠虎杖()\n乌鸦法杖\n致命球法杖()\n暴风雨法杖\n泰拉棱镜()\n外星法杖()\n星尘细胞法杖()\n星尘之龙法杖()\n哨兵\n眼球激光塔()\n蜘蛛女王法杖()\n寒霜九头蛇法杖\n月亮传送门法杖()\n七彩水晶法杖()\n弩车手杖/魔杖/法杖()\n爆炸机关手杖/魔杖/法杖()\n爆炸烈焰手杖/魔杖/法杖()\n闪电光环手杖/魔杖/法杖()\n鞭()\n皮鞭\n荆鞭\n脊柱骨鞭\n鞭炮\n冷鞭\n迪朗达尔\n暗黑收割\n晨星\n万花筒\n其他武器爆炸物\n炸弹\n粘性炸弹\n弹力炸弹()\n甲虫炸弹()\n雷管\n粘性雷管()\n弹力雷管()\n炸弹鱼()\n神圣手榴弹\n可放置\n雪球发射器\n大炮\n兔兔炮\n地雷\n(机关)\n(熔岩)\n工具武器\n信号枪",
  "content_length": 1200,
  "chinese_ratio": 0.954,
  "categories": [
    "有对应旧版页面的主空间页面",
    "武器物品",
    "掉落物品",
    "近战武器",
    "困难模式独有物品",
    "电脑版内容",
    "主机版内容",
    "前代主机版内容",
    "移动版内容",
    "3DS版内容",
    "3DS正式版中引入的实体"
  ]
}