{
  "title": "坐骑",
  "content": "关于坐骑叠加各种移动配饰后的跳跃/飞行高度对比，参见跳跃高度对比§组合。\n坐骑是玩家可以用于运输或制造伤害的生物或物件，作用相当于载具。当使用了坐骑召唤物品时，它会对玩家施加一个无限增益，生成坐骑，并将玩家放于其上或其中。坐骑的移动可用玩家的常规移动键来控制。像宠物和仆从一样，坐骑可以无限使用，其召唤物品不会被消耗掉。一次只能有一个坐骑生效。当玩家死亡时坐骑会自动卸掉。\n武器和工具（以及除了钩爪外的任何其他物品）都可以在骑着钻头坐骑()之外的任何坐骑时使用。\n所有坐骑物品都能放置在坐骑栏中然后用快速坐骑即可召唤，也可以染色。骑上坐骑会提供短时间的光照（蜜蜂和鳞甲怪除外）。\n目前一共有 27 种坐骑，每种都有不同的能力和移动属性。所有坐骑召唤物品都为08*稀有度，除了虾松露和女巫扫帚为12*稀有度，以及那些大师模式独有坐骑，它们具有13*稀有度。\n坐骑召唤物品没有修饰语，因此也不能重铸。\n\n目录\n\n1 困难模式之前\n2 困难模式\n3 仅限大师模式\n\n3.1 困难模式之前\n3.2 困难模式\n\n4 备注\n5 成就\n6 小贴士\n7 花絮\n() 跳到敌怪头上会对敌怪造成召唤伤害\n在水中会漂浮\n坠落速度加倍\n掉落伤害减半\n\n42\n\n21102 (坠落)\n\n史莱姆王\n\n蜜蜂()内部坐骑 ID：5\n涂蜜护目镜()\n\n在陆地上很慢\n快速飞行、飞行时间有限、自动悬停\n消除掉落伤害\n在液体中会取消骑乘，除非能在液体上行走（例如，使用水上漂药水或水上漂靴）\n\n654\n\n10（走）31（飞）\n\n蜂王\n\n龟()内部坐骑 ID：4\n硬鞍()\n\n在陆地上很慢\n在水中很快\n()允许水下呼吸\n\n4\n\n10（走）36（游）\n\n金匣和钛金匣()\n\n兔兔()内部坐骑 ID：1\n绒毛胡萝卜()\n\n跳得更高\n随着跑动加速\n消除掉落伤害\n\n12\n\n39\n\n渔夫(第 5 个任务后奖励)\n\n蹦蹦跷()内部坐骑 ID：43\n蹦蹦跷()\n\n跳得更高\n降低掉落伤害\n坠落速度大幅提高\n\n4 (正常)20 (高)\n\n29\n\n派对女孩(25 GC)\n\n高尔夫球车()内部坐骑 ID：17\n高尔夫球车钥匙()\n\n全速时会对敌怪造成召唤伤害\n向玩家面对的方向发出一道光锥\n降低掉落伤害，跳的更高\n\n28\n\n41\n\n高尔夫球手()(50 GC，打败骷髅王后 且高尔夫分数达到 2000 或更高)\n\n火烈鸟()内部坐骑 ID：37\n贝壳哨()\n\n在水中会漂浮\n在水中游泳\n降低掉落伤害\n高加速度\n\n15\n\n31\n\n动物学家()(20 GC，怪物图鉴填充了 25%/135 个条目)\n\n花马()内部坐骑 ID：40\n蒙尘牛皮鞍()\n\n跳得更高\n随着跑动加速\n全速奔跑时会对敌怪造成召唤伤害\n\n12\n\n46\n\n动物学家()(25 GC，怪物图鉴填充了 30%/162 个条目)\n\n骏马()内部坐骑 ID：41\n皇家鎏金鞍()\n\n跳得更高\n随着跑动加速\n全速奔跑时会对敌怪造成召唤伤害\n\n12\n\n46\n\n动物学家()(25 GC，怪物图鉴填充了 30%/162 个条目)\n\n黑马()内部坐骑 ID：42\n黑铆钉鞍()\n\n跳得更高\n随着跑动加速\n全速奔跑时会对敌怪造成召唤伤害\n\n12\n\n46\n\n动物学家()(25 GC，怪物图鉴填充了 30%/162 个条目)\n\n熔岩鲨()内部坐骑 ID：49\n过热的血()\n\n在液体中游得很快\n免疫熔岩\n在陆地上时减速\n掉落伤害降低到 1\n不会自动爬上物块（需要跳跃）\n\n2\n\n10 (走) 73 (游)\n\n黑曜石匣()和狱石匣()\n\n困难模式\n\n坐骑\n\n物品\n\n描述\n\n高度（英尺）\n\n速度（mph）\n\n来源\n\n蛇蜥怪()内部坐骑 ID：14\n远古号角()\n\n移动速度快\n加速度较快\n二连跳\n增加跳跃高度\n冲锋通过敌怪会对敌怪造成召唤伤害\n掉落伤害降低 80%\n\n28\n\n41\n\n蛇蜥怪()\n\n狼()内部坐骑 ID：52\nLilith的项链()\n\n将玩家转换成狼\n\n30\n\n49\n\n狼 命名为\"Wolfpet\"或者\"Wolf Pet\"的旅行模式人物.\n\n独角兽()内部坐骑 ID：10\n恩赐苹果()\n\n奔跑速度快\n二连跳\n全速奔跑时会对敌怪造成召唤伤害\n掉落伤害降低 80%\n\n39 (普通) 48 (二连跳)\n\n61\n\n独角兽\n\n猪龙()内部坐骑 ID：2\n带鳞松露()\n\n有限飞行时间\n奔跑速度快\n消除掉落伤害\n\n218\n\n46\n\n地下神圣/腐化/猩红-雪原中钓鱼\n\n羽翼史莱姆()内部坐骑 ID：50\n明胶女式鞍()\n\n有限飞行时间\n跳得更高，移动得更快\n用▼ 下+ ↷ 跳来水平悬停。\n跳到敌怪头上会对敌怪造成召唤伤害\n消除掉落伤害\n在水中会漂浮\n\n146\n\n33 (地面)56 (垂直上升)102 (坠落)34 (垂直悬停)58 (空中水平移动)\n\n史莱姆皇后()\n\n鲁道夫内部坐骑 ID：0\n驯鹿铃铛\n\n有限飞行时间\n奔跑与飞行都快\n消除掉落伤害\n\n194~582\n\n61\n\n冰雪女王\n\n鳞甲怪()内部坐骑 ID：9\n扰脑器()\n\n移动速度快\n自动向敌怪发射激光\n掉落伤害降到 1\n\n40\n\n41\n\n鳞甲怪枪手()\n\nUFO()内部坐骑 ID：7\n宇宙车钥匙()\n\n无限飞行\n在液体中会取消骑乘\n\n∞\n\n41（水平/垂直）58（对角线）\n\n火星飞碟()\n\n女巫扫帚()内部坐骑 ID：23\n女巫扫帚()\n\n无限飞行\n3 格高\n无法穿过某些平台下落\n\n∞\n\n46 (水平)41 (垂直)\n62 (对角线)\n\n哀木(仅限专家模式)\n\n可爱猪龙鱼()内部坐骑 ID：12\n虾松露()\n\n无限飞行\n在液体中有伤害/移动奖励\n在陆地上时减速\n\n∞\n\n33（水平）53（对角线）41（垂直）82（浸没于液体中）67（生命值 <50%，或离开液体后 6 秒钟内）5（如果与物块接触）\n\n猪龙鱼公爵(仅限专家模式)\n\n钻头()内部坐骑 ID：8\n钻头控制装置()\n\n无限飞行\n能挖掘地块（⚒ 使用/攻击）\n骑乘时无法使用物品\n\n∞\n\n31（水平）41（垂直）51（对角线）\n\n制作\n\n仅限大师模式\n困难模式之前\n\n坐骑\n\n物品\n\n描述\n\n高度（英尺）\n\n速度（mph）\n\n来源\n\n书()内部坐骑 ID：48\n暗黑魔法师巨著()\n\n有限飞行；固定最大高度\n消除掉落伤害\n\n41\n\n黑暗魔法师()\n\n困难模式\n\n坐骑\n\n物品\n\n描述\n\n高度（英尺）\n\n速度（mph）\n\n来源\n\n山羊()内部坐骑 ID：47\n山羊骷髅头()\n\n奔跑速度快\n二连跳\n全速奔跑时会对敌怪造成召唤伤害\n掉落伤害降低 80%\n\n39\n\n61\n\n血肉墙\n\n海盗船()内部坐骑 ID：44\n黑斑()\n\n无限飞行\n全速飞行时会对敌怪造成召唤伤害\n5 格高\n\n∞\n\n36 (水平)\n41 (垂直)\n54 (对角线)\n\n荷兰飞盗船()\n\n树()内部坐骑 ID：45\n魔法树枝()\n\n奔跑速度极快\n全速奔跑时会对敌怪造成召唤伤害\n\n81\n\n哀木\n\n圣诞老人坦克()内部坐骑 ID：46\n玩具坦克()\n\n自动向敌怪射击\n二连跳\n掉落伤害降低到 1\n\n12\n\n41\n\n圣诞坦克\n\n备注\n虽然坐骑不会改变玩家的宽度，但骑上坐骑会增加玩家的高度。比如说，海盗船坐骑和独角兽坐骑会将玩家的高度增加到 5 格，而大部分坐骑，比如粘鞍和远古号角会将玩家的高度增加到 4 格。\n坐骑也受盔甲套装的套装奖励效果影响，例如，如果穿着全套神圣盔甲骑上独角兽坐骑，独角兽会具有脉动的外轮廓（不过，一些染料，比如冥王染料，会使其难以辨认）。\n用幽灵靴或任意其升级物飞行的时候开启骑乘可能会暂时将其粒子效果恢复为火箭靴的效果。\n成就\n 骑兵 • “装备坐骑。”第一次装备坐骑。()类别： 收藏家\n小贴士\n可以用机械或 Hoik 实现与坐骑兼容的门户，允许玩家骑着坐骑进出各个区域。用高门亦可。\n宇宙车钥匙、女巫扫帚、虾松露、钻头控制装置、和黑斑都能给予玩家无限飞行能力。\n花絮\n鲁道夫是第一个被引入《泰拉瑞亚》的坐骑，也是游戏中唯一一个全平台可用的坐骑。\n蜜蜂坐骑最为接近于此，只任天堂中没有。其他坐骑则仅限于某些版本。\n哀木是唯一可以同时掉落两个坐骑召唤物品的敌怪。\n独角兽坐骑是唯一有自己成就的坐骑，骑着它时发射彩虹枪可以得到此成就。\n召唤工具宠物\n蚊子琥珀\n格林奇宝宝的恶作剧口哨\n保险丝球()\n竹叶()\n眩晕花蜜()\n伯尼的钮扣()\n双足翼龙蛋()\n小鸟拨浪鼓()\n蓝鸡蛋()\n骨头钥匙\n骨头拨浪鼓()\n罐中脑()\n胡萝卜(电脑版、和)\n天界魔棒()\n同伴方块()\n宇宙滑板()\n诅咒树苗\n失效探测器()\n独眼巨鹿眼球()\n狗哨()\n龙蛋()\n吞噬怪骨头\n桉树汁()\n奇异咀嚼玩具()\n眼骨()\n弹簧眼\n鱼\n冰冻王冠()\n满月尖叫玩具()\nGato蛋()\n咕噜咪的花()\n发光郁金香()\n闪电胡萝卜()\n蜥蜴蛋\n魔法南瓜子\n怪物肉()\n泥芽()\n花蜜\n食人魔棍棒()\n华丽暗影钥匙()\n微型双子魔眼()\n鹦鹉饼干\n月亮乌贼()\n世纪之花幼苗()\n海猪肉()\n疯狂骷髅头()\n王室美食()\n华美甜点()\n机器人骷髅头()\n皇家美味()\n海草\n幼苗\n鲨鱼鱼饵()\n灌木星星()\n地狱蛋糕块()\n闪耀蜂蜜()\n蜘蛛卵\n毛绒Spiffo()\n星之果实()\n奇异发光蘑菇\n可疑咧嘴眼球()\n碑牌碎片()\n塔塔酱\n最土的块()\n提基图腾\n玩具雪橇\n霉运纱线\n蠕动残骸()\n和风鱼\n\n脑子\n碎心\n蜜蜡\n卷心菜\n金海草\n节日装饰品\n老手杖\n培养皿\n黄金锅\n闪亮黑板\n可疑苹果\n火鸡羽毛\n血液瓶\n狼牙\n坐骑\n远古号角()\n黑铆钉鞍()\n恩赐苹果()\n扰脑器()\n宇宙车钥匙()\n暗黑魔法师巨著()\n钻头控制装置()\n蒙尘牛皮鞍()\n绒毛胡萝卜()\n明胶女式鞍()\n山羊骷髅头()\n高尔夫球车钥匙()\n硬鞍()\n魔法树枝()\n涂蜜护目镜()\nLilith的项链()\n贝壳哨()\n蹦蹦跷()\n驯鹿铃铛\n皇家鎏金鞍()\n带鳞松露()\n虾松露()\n粘鞍()\n过热的血()\n黑斑()\n玩具坦克()\n女巫扫帚()\n矿车\n木矿车()\n矿车\n机械矿车()\n沙漠矿车()\n鲤鱼矿车()\n蜜蜂矿车()\n瓢虫矿车()\n猪龙矿车()\n向日葵矿车()\n恶魔地狱矿车()\n蘑菇矿车()\n紫晶矿车()\n黄玉矿车()\n蓝玉矿车()\n翡翠矿车()\n红玉矿车()\n钻石矿车()\n琥珀矿车()\n甲虫矿车()\n彩虹猫矿车()\n派对矿车()\n荷兰人矿车()\n蒸汽朋克矿车()\n棺材矿车()\n挖掘鼹鼠矿车()\n放屁车()\n泰拉放屁车()\n照明宠物\n暗影珠\n猩红之心()\n魔法灯笼()\n仙灵铃铛\n飞眼怪蛋()\n石巨人守卫()\n光之珠宝()\n南瓜香薰蜡烛()\n妖灵瓶\n可疑触手()\n便携式收纳\n钱币槽()\n虚空袋()\n其他工具探索\n双筒望远镜\n芦苇呼吸管\n魔镜\n冰雪镜()\n手机()\n贝壳电话()\n三叉戟\n传送枪()\n混沌传送杖\n和谐传送杖()\n伞\n悲剧雨伞()\n魔法海螺()\n恶魔海螺()\n影响地形\n物块放置魔棒\n土魔杖\n沙堡桶()\n再生法杖\n再生之斧()\n环境改造枪\n泰拉改造枪()\n割草机()\n堆石器()\n电路\n扳手\n蓝扳手\n绿扳手\n黄扳手()\n五彩扳手()\n钢丝钳\n宏伟蓝图()\n致动魔杖()\n刷漆()\n漆刷\n幽灵漆刷\n涂漆滚刷\n幽灵涂漆滚刷\n漆铲\n幽灵漆铲\n其他\n提桶\n无底桶()\n吸收绵()\n土炸弹()\n粘性土炸弹()\n干炸弹()\n蜂蜜炸弹()\n熔岩炸弹()\n湿炸弹()\n虫网\n防熔岩虫网()\n金虫网()\n镰刀\n泡泡魔棒\n钓竿\n高尔夫球杆()\n高尔夫口哨()\n耍蛇者长笛()\n雨歌()\n常春藤()\n负重石()\n停用()\n小动物友谊指南()\n停用()\n环境保护指南()\n停用()\n和平共处指南()\n停用()",
  "content_length": 4787,
  "chinese_ratio": 0.962,
  "categories": [
    "游戏机制"
  ]
}