{
  "title": "符文巫师",
  "content": "符文巫师困难模式独有 经典 专家 大师详细信息类型不死敌怪环境 洞穴 AI 类型法师 AI伤害200/400/600 （接触）80160240 （符文爆破弹）最大生命值600/1200/1800防御30击退抗性70%/73%/76%敌怪旗符文巫师旗()免疫掉落钱币50 SC1 GC25 SC物品（数量）掉落率符文帽100%符文长袍100%生成的射弹生成的射弹生成的射弹符文爆破弹声音受伤害被击杀符文爆破弹传送内部 NPC ID：172内部射弹 ID：129\n符文巫师是个稀有的困难模式法师敌怪，出现在洞穴层下部。在生成时，他会动手向玩家发射可穿透物块的亮绿色魔法符文爆破弹射弹，类似于其他法师敌怪，如火焰小鬼和暗黑法师。然而，与烈焰球不同，符文巫师的射弹无法以任何方式摧毁。他会造成极其高额的接触伤害，并且会在发射六枚射弹后传送至新位置。符文巫师在死亡时总是会掉落符文帽和符文长袍。\n它是少数能被生命体分析机()或其升级物探测到的实体之一。符文巫师需要 10 击杀来完成怪物图鉴条目和得到相应的旗帜，而非通常的 50 击杀。\n\n目录\n\n1 备注\n2 小贴士\n3 花絮\n备注\n符文巫师只在一定深度以下才能生成。此深度可以通过将地下层底部和地狱层底部的绝对深度相加然后除以 2 来确定。由于世界生成过程是随机化的，对于不同的世界这个值会有所不同。\n通常，有熔岩的区域可以作为很好用的指示器来指明哪里会生成符文巫师。\n小贴士\n对抗符文巫师的一个简单方法就是不断攻击他。这基本上会让他瘫掉，防止它攻击和传送。对他造成着火了！之类的减益会是对抗他的非常有效的方法。\n能让符文巫师瘫掉的可行武器包括食人鱼枪、诸如巨兽鲨等具有高开火速率的武器、以及大多数召唤武器。\n尽管符文巫师并不会尝试接触玩家作为其攻击的一部分，但它会造成极高的接触伤害，3 下左右就足以干掉大多数玩家。他的射弹造成的伤害要低得多，但他对于只有弱困难模式物品的玩家来说依然可能非常危险，尤其是当他生成在一个无法到达的位置时。\n在大师模式()中，其接触伤害往往足以秒杀玩家。\n由于其超高的接触伤害，建议使用远距离武器对抗符文巫师。但是，由于他生成在狭窄的洞穴群中，要做到这点可能会很困难。\n花絮\n符文巫师可视为是蒂姆的困难模式版本。掉落的时装物品非常类似于蒂姆所掉落的物品。二者也有类似的生成深度和攻击模式，并且都会掉落只能通过打败它们得到的独特物品。另外，根据怪物图鉴的说法，符文巫师是蒂姆的哥哥。\n但是，和蒂姆不同，符文巫师的生成速度完全无法由玩家手动提高。\n由于符文巫师生成速度超低并且对生成位置还有限制，他可视为是游戏中最稀有的敌怪之一。\n符文巫师的接触伤害在所有敌怪中排名第二，他的伤害则是伤害游戏中第三高的。其接触伤害和海盗船长的炮弹以及骷髅狙击手的狙击弹相当。他的伤害仅次于地牢守卫和在白天的光之女皇()。\n符文巫师的 怪物图鉴条目：“蒂姆的哥哥，更强大，长得也更帅。他也喜欢高温环境，但不喜欢极热环境。”",
  "content_length": 1238,
  "chinese_ratio": 0.984,
  "categories": [
    "电脑版内容",
    "主机版内容",
    "前代主机版内容",
    "移动版内容",
    "3DS版内容",
    "洞穴_NPC",
    "不死敌怪_NPC",
    "法师_AI_NPC",
    "困难模式独有_NPC",
    "3DS正式版中引入的实体"
  ]
}