{
  "title": "鳞甲怪",
  "content": "电脑版//：此信息仅适用于的《泰拉瑞亚》。鳞甲怪详细信息类型敌怪环境 火星暴乱 \n关于相似外观的坐骑，参见扰脑器。\n鳞甲怪是困难模式中，石巨人被击败后，出现在火星暴乱事件中的敌怪。它由鳞甲怪和骑着它的鳞甲怪枪手组成。它们有各自独立的血条，也可以被独立杀死。一旦其中一员被杀，另一个还会继续战斗。\n\n目录\n\n1 部分\n2 备注\n3 小贴士\n4 花絮\n\n4.1 怪物图鉴条目\n\n备注\n如果鳞甲怪在鳞甲怪枪手之前被杀掉，枪手就回变成普通的激光枪手，这意味着他不再会掉落独有的旗帜和扰脑怪坐骑召唤物。它必须在还骑着鳞甲怪，被视为鳞甲怪枪手时才会掉落。考虑到需要优先杀死枪手，建议避免使用熔岩做成的陷阱。\n鳞甲怪自身有火星暴乱事件中非Boss敌怪中最高的攻击伤害。\n小贴士\n使用沙漠虎杖或者是由外星法杖召唤出的UFO都有助于在杀死鳞甲怪前先杀死枪手，这有助于刷扰脑怪物品。\n任何远程武器稍微离地发射，将更容易优先攻击鳞甲怪枪手而不是鳞甲怪，这也是一种可行的策略，因为鳞甲怪枪手有着相比它的坐骑更低的生命。\n花絮\n怪物图鉴条目鳞甲怪：“这些生物原产于火星本土，它们的功能与马相似。换言之，它们就是眼睛会发射激光的马。”鳞甲怪枪手：“精英激光枪手经常会骑上这些强大的异星生物作为骑兵参战。如果坐骑死了，他们就会徒步继续战斗。”\n尽管怪物图鉴条目的描述如此，鳞甲怪本身并不会发射任何激光或射弹，只有鳞甲怪枪手会。",
  "content_length": 598,
  "chinese_ratio": 0.986,
  "categories": [
    "电脑版内容",
    "主机版内容",
    "移动版内容",
    "火星暴乱_NPC",
    "敌怪_NPC",
    "骑士_AI_NPC",
    "战士_AI_NPC",
    "困难模式独有_NPC"
  ]
}