{
  "title": "蜘蛛家具",
  "content": "电脑版//：此信息仅适用于的《泰拉瑞亚》。\n主文章：家具套装\n\n蜘蛛家具是用蜘蛛窝块制作的家具物品，而光面大理石块是用蜘蛛牙和蛛网在工作台制作的。有 20 种不同的蜘蛛家具物品。\n\n产物材料制作站蜘蛛平台()2蜘蛛窝块()徒手蜘蛛工作台()蜘蛛窝块()10蜘蛛吊灯()蜘蛛窝块()4火把4链条铁砧或铅砧蜘蛛浴缸()蜘蛛窝块()14锯木机蜘蛛床()蜘蛛窝块()15丝绸5蜘蛛书架()蜘蛛窝块()20书10蜘蛛时钟()蜘蛛窝块()10任何铁锭3玻璃6蜘蛛梳妆台()蜘蛛窝块()16蜘蛛钢琴()蜘蛛窝块()15骨头4书蜘蛛沙发()蜘蛛窝块()5丝绸2蜘蛛马桶()蜘蛛窝块()6蜘蛛烛台()蜘蛛窝块()5火把3工作台蜘蛛蜡烛()蜘蛛窝块()4火把蜘蛛椅()蜘蛛窝块()4蜘蛛箱()蜘蛛窝块()8任何铁锭2蜘蛛门()蜘蛛窝块()6蜘蛛灯()火把蜘蛛窝块()3蜘蛛灯笼()蜘蛛窝块()6火把蜘蛛水槽()蜘蛛窝块()6水桶蜘蛛桌()蜘蛛窝块()8\n花絮\n蜘蛛家具是在泰拉瑞亚社区论坛由用户“Braquen”建议的。\n蜘蛛家具是困难模式物品，因为尽管爬墙蜘蛛也是蜘蛛，但它不掉落蜘蛛牙，只有黑隐士才会掉落。\n生命木家具\n竹子家具()\n仙人掌家具\n南瓜家具\n蘑菇家具\n花岗岩家具()\n大理石家具()\n陨石家具()\n水晶家具()\n玻璃家具()\n沙岩家具()\n火星家具()\n蜘蛛家具()\n天域家具\n冰冻家具()\n珊瑚礁家具()\n蜂蜜家具\n史莱姆家具\n气球家具()\n骨头家具\n血肉家具\n病变家具()\n蒸汽朋克家具\n丛林蜥蜴家具\n月亮家具()\n日耀家具\n星旋家具\n星云家具\n星尘家具\n黑曜石家具\n地牢家具\n金家具",
  "content_length": 693,
  "chinese_ratio": 0.986,
  "categories": [
    "电脑版内容",
    "主机版内容",
    "移动版内容",
    "可制作的物品",
    "锯木机",
    "徒手",
    "工作台",
    "铁砧或铅砧",
    "家具套装"
  ]
}