{
  "title": "阴森家具",
  "content": "主文章：家具套装\n\n阴森家具是用阴森木制作的家具物品，阴森木可以通过打败南瓜月事件期间的树精和哀木得到。有() 20 / (前代) 18 /  5 种不同的阴森家具物品。\n\n产物材料制作站阴森木平台2阴森木徒手阴森工作台阴森木10仅限   ：阴森吊灯阴森木4火把4链条铁砧或铅砧阴森浴缸()阴森木14锯木机仅限   ：阴森床阴森木15丝绸5阴森书架()阴森木20书10阴森时钟()任何铁锭3玻璃6阴森木10仅限   ：阴森梳妆台阴森木16仅限   ：阴森钢琴骨头4阴森木15书阴森沙发()阴森木5丝绸2阴森马桶()阴森木6仅限 ：阴森床阴森木15丝绸5工作台阴森大烛台()阴森木5火把3阴森蜡烛()阴森木4火把阴森椅阴森木4仅限 ：阴森吊灯阴森木4火把4链条阴森箱()阴森木8任何铁锭2阴森门阴森木6仅限 ：阴森梳妆台阴森木16阴森灯()火把阴森木3阴森灯笼()阴森木6火把仅限 ：阴森钢琴骨头4阴森木15书阴森水槽()阴森木6水桶阴森桌阴森木8\n生命木家具\n竹子家具()\n仙人掌家具\n南瓜家具\n蘑菇家具\n花岗岩家具()\n大理石家具()\n陨石家具()\n水晶家具()\n玻璃家具()\n沙岩家具()\n火星家具()\n蜘蛛家具()\n天域家具\n冰冻家具()\n珊瑚礁家具()\n蜂蜜家具\n史莱姆家具\n气球家具()\n骨头家具\n血肉家具\n病变家具()\n蒸汽朋克家具\n丛林蜥蜴家具\n月亮家具()\n日耀家具\n星旋家具\n星云家具\n星尘家具\n黑曜石家具\n地牢家具\n金家具",
  "content_length": 621,
  "chinese_ratio": 1.0,
  "categories": [
    "可制作的物品",
    "锯木机",
    "徒手",
    "工作台",
    "铁砧或铅砧",
    "家具套装"
  ]
}