{
  "title": "圣骑士",
  "content": "圣骑士困难模式独有投掷攻击 经典 专家 大师详细信息类型敌怪环境 地牢 AI 类型战士 AI伤害100/200/300 （接触）120180270 （圣骑士锤）最大生命值5000/10000/15000防御50击退抗性100%敌怪旗圣骑士旗()免疫掉落钱币5 GC12 GC50 SC物品（数量）掉落率烧烤肋排()14.29%圣骑士锤6.67%12.89%圣骑士护盾10%19%生成的射弹生成的射弹生成的射弹圣骑士锤（敌方）声音受伤害被击杀内部 NPC ID：290内部射弹 ID：300\n圣骑士是罕见、强大的困难模式、世纪之花后的敌怪，在击败世纪之花后于地牢中生成。它免疫击退并通过快速地投掷能穿过物块并造成极大伤害的锤射弹来攻击。\n它是少数能被生命体分析机()或其升级物探测到的实体之一。圣骑士需要 25 次击杀以完成其怪物图鉴条目并获得对应旗帜，而非通常的 50 次击杀。[1]\n\n砖墙此区域的派系旗帜： \n圣骑士往往生成在有砖墙的地牢区域。它们也会生成在地牢的其他区域，但几率大大降低。\n\n目录\n\n1 备注\n2 小贴士\n3 花絮\n备注\n圣骑士是非常困难的敌怪。作为非 Boss 敌怪而言，他们的射弹攻击是异常灵活的，且能造成极大伤害。圣骑士的生命比骷髅王还高、对击退免疫、并且防御和月亮领主()与猪龙鱼公爵（在其第一形态中）一样，使他们难以击杀并且试图溜过去或者忽略他们也很危险。\n虽然圣骑士视觉高度是 4 格，但他们能够穿过 3 格高的走廊。\n圣骑士在移动或被攻击时不能扔锤子。\n圣骑士不太会瞄准视线之外的玩家。\n小贴士\n因为圣骑士受到伤害时他的攻击会被打断。快速开火的武器能完全阻止他攻击。\n大多数近战武器都能够足够快的打击，但圣骑士对击退的免疫和周围的其他敌怪可能会让这很难实现。\n也可以用快速开火的远程武器，但是，其他敌怪可能会挡路，让圣骑士能攻击。可以考虑使用穿透或爆炸射击。食人鱼枪也异常有效。\n有穿透能力的魔法武器可以起到很好的效果。值得注意的例子是高温射线枪（）、爆裂藤蔓、或魔法竖琴。一旦获得，也可以用暗影束法杖或彩虹枪。\n召唤武器特别适合干掉圣骑士。()如果已将圣骑士标记为目标，仆从几乎总是能足够快地对其进行打击来阻止其攻击。玩家可以专注于干掉其他敌怪并保持安全距离。沙漠虎杖()、泰拉棱镜()、暴风雨法杖、和乌鸦法杖是在这一进度时最好的可用仆从武器。\n由于圣骑士的视线被阻拦后通常会立即停止攻击，关上的门和墙（可能带有一格宽的开口）是一种安全屏障。能通过物块（如死神镰刀）攻击或通过小洞攻击的武器（如腐化者之戟或雨云魔杖）可以用来低风险地打败圣骑士。\n不推荐在较小的走廊中与其战斗，因为这样就没有躲避的余地，经常导致快速死亡。在更长的双向走廊中通过不断的后退同时攻击可能可以打败圣骑士，但在中途可能出现的其他敌怪依然会构成威胁。\n被圣骑士的身体击中所造成的伤害低于被它的锤击中的伤害，除非是在专家模式()或大师模式()中。\n在专家模式()中，圣骑士即使捡了钱币也会消失。\n花絮\n在所有地牢敌怪中，圣骑士在死亡时掉落数量最多的钱币。\n圣骑士在视觉上持有它会掉落的两种物品：圣骑士锤和圣骑士护盾。\n圣骑士掉落的钱币量是所有非 Boss 敌怪中第三多的，和海盗船长持平。\n在现实生活中，圣骑士（paladin）（也音译为“帕拉丁”）通常是英雄中的冠军（尤其是骑士）或崇高事业的捍卫者和提倡者。查理曼大帝（Charlemagne）麾下最初的 12 名骑士也被称为“圣骑士”。\n圣骑士的 怪物图鉴条目：“在很久以前，这些强大的不死骑士曾经守护着一座繁华的城市，后来一个巨大的诅咒降临到他们身上。”\n现在会掉落烧烤肋排。\n因算法改变导致的掉落率变化:\n圣骑士锤：由 6.67% / 9.78% 提升至 6.67% / 12.89%。\n圣骑士护盾：由 9.33% / 13.56% 提升至 10% / 19%。任天堂任天堂3DS正式版：引入。",
  "content_length": 1630,
  "chinese_ratio": 0.965,
  "categories": [
    "电脑版内容",
    "主机版内容",
    "前代主机版内容",
    "移动版内容",
    "3DS版内容",
    "地牢_NPC",
    "敌怪_NPC",
    "战士_AI_NPC",
    "困难模式独有_NPC",
    "3DS正式版中引入的实体"
  ]
}