{
  "title": "沙漠幽魂",
  "content": "电脑版//：此信息仅适用于的《泰拉瑞亚》。沙漠幽魂困难模式独有 经典 专家 大师详细信息类型敌怪环境 地下沙漠 + 地下腐化之地 地下沙漠 + 地下猩红之地 AI 类型法师 AI伤害40/80/120 （接触） 6088132 （沙漠幽魂诅咒）最大生命值220/440/660防御20击退抗性100%敌怪旗沙漠幽魂旗()免疫掉落钱币12 SC30 SC物品（数量）掉落率一次只会掉落 2 个物品中的一个沙漠幽魂灯()2.5%神灵诅咒()3.25%生成的射弹生成的射弹生成的射弹沙漠幽魂诅咒声音受伤害被击杀沙漠幽魂诅咒传送内部 NPC ID：533内部射弹 ID：596\n沙漠幽魂是一种困难模式敌怪，出现于腐化或猩红的地下沙漠生物群系。\n相较于其他敌怪，沙漠幽魂有一种独特的攻击方式。当它接近玩家的时候，沙漠幽魂会发射一种紫色的追踪弹，这种追踪弹会逐渐加速靠近玩家，并可以穿过物块。在飞行一段时间后追踪弹会产生小范围爆炸。射弹不造成伤害，但射弹产生的爆炸会造成伤害。和其他法师相同，沙漠幽魂在攻击后会传送位置，然后重复这一过程。\n\n小贴士\n在狭窄的空间里，追踪弹爆炸需要时间，趁其间隙直接击杀沙漠幽魂是更好的策略。\n\n花絮\n沙漠幽魂指的是灵怪(英文中称其为\"genies\")，这类看不见的心灵的神话生物通常与古代和现代的阿拉伯伊斯兰教神话有关。\n沙漠幽魂和沙漠幽魂灯的联系是对《阿拉丁神灯》的引用，这个故事出自阿拉伯民间故事集《一千零一夜》，故事中的主角通过摩擦油灯来召唤一个神灯精灵，精灵将实现拥有者的愿望。\n沙漠幽魂的 怪物图鉴条目：“远古魔法腐化了曾经友善的沙漠神灵的心智，将他们满怀敌意地从灯中放出。”",
  "content_length": 704,
  "chinese_ratio": 0.963,
  "categories": [
    "电脑版内容",
    "主机版内容",
    "移动版内容",
    "地下沙漠_NPC",
    "地下腐化之地_NPC",
    "地下猩红之地_NPC",
    "敌怪_NPC",
    "法师_AI_NPC",
    "困难模式独有_NPC"
  ]
}