{
  "title": "海洋",
  "content": "海洋是一个生物群系，可以在世界的左侧和右侧找到，包括世界最东侧和最西侧 338 格（676 英尺）的区域[1][2]。它由一片沙滩和延伸到地图末端的一大片水域组成，有着偶尔会成团生成的贝壳堆。地面上会长出棕榈树，并且可以收割以获取棕榈木。贝壳和海星在地面和水下都很常见，且会随时间推移生成。海床上还长有珊瑚。\n海洋的敌怪包括螃蟹、粉水母和鲨鱼。乌贼和海蜗牛会罕见地出现在水下，并且分别会掉落黑墨水和紫黏液。海洋中会出现的小动物包括海豚、海鸥、海马、和海龟。\n海洋通常会包含水中箱，其中有和水相关的拾取物。\n\n目录\n\n1 内容\n2 NPC 快乐\n3 备注\n4 生成变体种类\n\n4.1 海洋洞穴\n4.2 佛罗里达风格\n\n5 小贴士\n6 花絮\n独特掉落来自鲨鱼：\n鲨鱼鳍潜水头盔（罕见）鲨鱼风筝（在大风天）\n来自螃蟹或鲨鱼：\n鲜虾三明治（罕见）\n来自乌贼：\n黑墨水\n来自海蜗牛：\n紫黏液\n来自粉水母：\n水母项链（罕见）荧光棒粉水母风筝（在大风天）\n来自猪龙鱼公爵：\n猪龙鱼公爵面具猪龙鱼公爵纪念章猪龙鱼之翼猪龙鱼链球利刃台风暴风雨法杖泡泡枪海啸宝藏袋（在专家模式中掉落，包含虾松露）海猪肉（在大师模式中罕见掉落）猪龙鱼公爵圣物（在大师模式中掉落）\n来自困难模式下的任何敌怪：\n海盗地图（罕见）\n来自地形/植被：\n珊瑚贝壳堆贝壳涡螺壳香螺壳旋螺壳海星棕榈木橙绿海藻\n来自摇晃棕榈树：\n椰子香蕉臭蛋（万圣节）\n来自钓鱼：\n鳟鱼金枪鱼红鲷鱼虾掠夺鲨锯齿鲨剑鱼粉水母（鱼饵）海洋匣（仅限困难模式之前）海边匣（仅限困难模式）\n来自渔夫任务：\n小丑鱼金枪鱼须船长（仅限困难模式）\n售卖来自海盗 (NPC)：\n鹦鹉饼干\n任何快乐 NPC 的商店：\n海洋晶塔\n音乐\n海洋白天海洋夜晚海洋（异界版）\n\nNPC 快乐\n海洋喜爱无喜欢海盗发型师()渔夫反感向导爆破专家巫师讨厌无更多信息，参见 NPC 快乐。\n备注\n与其他拥有游泳 AI 和水母 AI 的敌怪一样，海洋敌怪只会侦测并接近处于至少一格深的水中的玩家。\n如果海洋的沙滩部分延伸到陆地内足够远，就可能生成地表沙漠敌怪，但靠近水的区域不会长出沙漠植物。\n在困难模式中，腐化/猩红或神圣能将所有沙块转化为黑檀沙块/猩红沙块或珍珠沙块，这可以让腐化沙漠/猩红沙漠或神圣沙漠敌怪生成。\n腐化/猩红或神圣可以蔓延到世界边界以外的沙块上。\n在海洋中钓鱼时，游戏会检查浮标位置而非玩家位置。浮标必须位于海洋生物群系且在地表以上才会钓上海洋渔获。[3]\n此外，海洋必须保持纯净，否则腐化/猩红或神圣渔获会覆盖海洋渔获。\n\n有时候海床会生成在地表层以下，导致会出现一点地下的背景并且沙块上会长出海草。\n如果海床足够低，就有可能在海洋底部找到生命水晶、沙漠地下小屋、和露营地。\n海洋生物群系无法被人工创造，也无法被扩展。\n生成变体种类\n海洋洞穴\n 世界左侧的一个海洋洞穴的地图视图。\n与地牢在世界的同一侧的海洋有 1/3 (33.33%) 几率在生成时带有一个洞穴[4]，由一条充满水的隧道构成，有着硬化沙块天花板。这条隧道有额外机会生成水中箱，包含每个主要物品的几率都相同。其中装饰着从沙上长出来的长条海草。\n在 Drunk world、Celebrationmk10、和 Get fixed boi 世界中总是会生成海洋洞穴。\n\n佛罗里达风格\n 世界右侧的一个佛罗里达风格海洋的地图视图。\n 世界左侧的一个带有海洋洞穴的佛罗里达风格海洋的地图视图。\n世界有 1/4 (25%) 几率会把其中一个海洋生成为佛罗里达风格。[5]这种变体会反转海滩的坡度，长长的海滩会在靠近世界边缘的地方变得更陡峭。\n\n小贴士\n关于在海洋中穿行的技巧，参见指南:在海洋生存。\n如果玩家探索海洋时没有装备恰当的配饰，就有溺水的风险。除了充足的治疗药水外，还要携带一些辅助呼吸的物品和药水（如芦苇呼吸管和鱼鳃药水）、用来快速回家的魔镜、以及帮助游泳的脚蹼。钩爪对于返回海面呼吸也有一定帮助。海神贝壳或其升级物可以完全消除呼吸的需要。\n玩家可以挖一条通到地狱的隧道来将海洋抽干，水在地狱会蒸发。\n另一种抽干海洋的办法是造一个气室，在其中倒一桶熔岩桶并在熔岩中放置一个背景物体（例如家具）。让水流进去会导致水消失，因为放置的物体会阻止黑曜石的生成。\n在困难模式中试图防止海洋生物群系被感染时，光是在海床下挖一道水平隔离带是不够的，因为世界的数据要稍微超出世界边缘。隔离带必须沿着海洋的海滩垂直建立以阻止腐化之地/猩红之地或神圣之地蔓延。\n海洋中有很多空间，使其成为大规模建造的良好地点，比如战斗场地或农场。\n虽然不可能将海洋生物群系向内陆进一步扩大，但玩家可以将水域扩大到天然生成的海滩的内缘处。\n花絮\n《海洋夜晚》（Ocean Night）音乐在 1.4.0.1() 更新前是、 前代、和任天堂独有的。\n佛罗里达风格的海洋生成时有可能会带有海洋洞穴。\n海洋鱼通常比绿洲渔获有更高优先级，因为海洋天然也是沙漠。不过，如果海洋被转化为神圣，神圣渔获会比海洋渔获具有更高优先级，但在这种情况下钓鱼会有一半几率产生绿洲渔获（因为它此时被视为神圣沙漠）。\n现在在大风天时鲨鱼和粉水母会掉落各自的风筝。\n螃蟹和鲨鱼现在会掉落鲜虾三明治。\n现在钓鱼可以钓到海洋匣。\n现在可以通过摇晃棕榈树得到椰子和香蕉。}}\n\n现在有自己的树类型了。\n贝壳和海星已添加。\n试图在海洋里用松露虫钓鱼会召唤猪龙鱼公爵。\n\n现在有自己的音乐了。\n金宝箱被替换为水中箱。\n新敌怪：海蜗牛和乌贼。\n海洋中的敌怪现在在困难模式中会掉落海盗地图。\n\n海洋的生成过程已改进，且变得稍微大了一点。\n现在海底会长出珊瑚。\n新敌怪：螃蟹、粉水母、鲨鱼。\n电脑正式版：引入。主机正式版：引入。\n 任天堂移动正式版：引入。\n任天堂3DS正式版：引入。\n生命树\n生命红木树()\n金字塔\n废墟建筑\n地下小屋",
  "content_length": 2417,
  "chinese_ratio": 0.968,
  "categories": [
    "有对应旧版页面的主空间页面",
    "电脑正式版中引入的实体",
    "主机正式版中引入的实体",
    "移动正式版中引入的实体",
    "3DS正式版中引入的实体",
    "环境",
    "电脑版内容",
    "主机版内容",
    "前代主机版内容",
    "移动版内容",
    "3DS版内容"
  ]
}